{
  "chunk_hash": "2810efec33cc13",
  "chunk_id": "Anthony_Villegas_2810efec33cc13_fd743041",
  "user_query": "to pat children especially on their foreheads it's normal in American culture but offensive in Hmong culture these two actions by Walt can be seen as unacceptable to the Hmong who get offended every time Walt does this what are we doing what do you want to do share your tools in the lice bag you can use one of these and you'll need one of these here I can't afford any of this I'll cover it you can pay me back on your first paycheck cool here you'll need something like that and this is what I'm looking for here too there you go not to but wouldn't I be needing some tools tools I've got but I'm not going to lend you my tool belt you can pick up tools as you go I really appreciate all this forget it no I really do thank you towards the end of the film Walt is no longer a racist angry anti-social human being he's someone who helps and cares about Thao and his family's well-being and also the rest of his Hmong neighbors Walt having become Thao's friend and mentor changes Thao's life for the better he's no longer timid",
  "movie_id": "그랜 토리노",
  "reviewer": "Anthony_Villegas",
  "chunk_index": 5
}