{
  "chunk_hash": "c3ac0be06f014c",
  "chunk_id": "무드킹_c3ac0be06f014c_6156c8d9",
  "user_query": "[음악] 영화 아메리칸 언더독 시작합니다 1992년 노던 벤치 생활에서 벗어나 처음으로 주전으로 뛰게 된 커트 워너 그러나 상대팀의 도발에도 더욱더 자신감 있게 플레이하는 커트 [음악] [박수] Come [음악] on 커트는 어떤 여자를 보고 첫눈에 반하게 되고 you need Barn and all the dan be great girl have no idea How happ [박수] [음악] makes bar [박수] [음악] [박수] [음악] you 하지만 여자는 이름을 알려주지 않는데 [음악] miss aust there That's ating contest congratulations foot seriously football was the most important thing my PO He's back in my life now but back then It was tough I wanted to make something my life as long as I have a b in my hands then I feel like everything going to be All right Do you like about it I guess different kind like you I'm brenda It's pleasure to meet you [음악] BR and something that I did can I at least get your phone number you don't want it What why wouldn't I why wouldn't I want your number I'm divorced and I got two kids so If I never see you again i TOT understand here [음악] 갑작스러운 커트의 방문에 크게 놀란 브렌다 그때 브렌다의 아들 잭이 문을 열어주는데 [음악] country They got you to huh down ok maybe country Ain't so bad After all you like trucks trucks dri what he means is He wants to drive a black truck Hey I'm kurt I'm here for brenda I'm Jenny Joe the mom kind of you to fix the radio my pleasure cute Can you please radi we Keep every room in the house it helps SA How do you know where I live the bar center at the bar wanted to meet your kids also want to give you this oh look I have to get Z to physical therapy so He's legally blind I hadn't really noticed that I'll see you around Hey It was really nice to",
  "movie_id": "아메리칸 언더독",
  "reviewer": "무드킹",
  "chunk_index": 1
}