{
  "chunk_hash": "d4b4ee23f8120b",
  "chunk_id": "유캔프리_UCANFREE_d4b4ee23f8120b_290a347c",
  "user_query": "well it certainly didn't show you were great well it certainly didn't show you were great well it certainly didn't show you were great well it certainly didn't show you were great hey I'm starved where are we gonna eat hey I'm starved where are we gonna eat hey I'm starved where are we gonna eat hey I'm starved where are we gonna eat hey I'm starved where are we gonna eat anywhere you want anywhere you want anywhere you want anywhere you want anywhere you want you really like this place you really like this place you really like this place you really like this place you really like this place I thought you would hate it cozy intimate I thought you would hate it cozy intimate I thought you would hate it cozy intimate I thought you would hate it cozy intimate I thought you would hate it cozy intimate it's exactly my style it's exactly my style it's exactly my style it's exactly my style it's exactly my style you looked really cute today in your meeting you looked really cute today in your meeting you looked really cute today in your meeting you looked really cute today in your meeting you looked really cute today in your meeting what are you saying what are you saying what are you saying what are you saying what are you saying I bet you didn't come to work today I bet you didn't come to work today I bet you didn't come to work today I bet you didn't come to work today I bet you didn't come to work today I mean I didn't see you I mean I didn't see you I didn't see you I mean I",
  "movie_id": "이프 온리",
  "reviewer": "유캔프리_UCANFREE",
  "chunk_index": 36,
  "entities": [],
  "relationships": []
}