{
  "chunk_hash": "c9f0a46b14282b",
  "chunk_id": "작스튜브ZAKSTUBE_c9f0a46b14282b_1818411e",
  "user_query": "[음악] 으 응 언니 꼴도 보기 싫다 아 아 노 남은 곳으로 가는 것 [음악] 예 안녕하세요 지금 줍니다 예 반갑습니다 아 사건의 지평선 님 반갑습니다 오늘은 제일 먼저 인사 드리네요 요인이한테 예 음 아직 시청 기분이 이제 항상 저 들면 갑자기 방송 하니까 시간 때도 정해지지 않고 그래서 예 오프닝이 조금 늦게 들어오십니다 80년 자몽 다 먹게 음식으로 좀 시간을 끌자면 네 제가 딱히를 끌었어요 딱지 딱 에 과태료를 물었는데 얕은 낮은 처음 받아 보러 가 들어 있습니다 가 뭐 뭘 위반한 위반 뭐 이거 가지고 나왔는데 장애인 주차장에 차를 댔다 라는 거죠 근데 이제 그것만 따지면 당연히 에 제가 100% 잘못 맞습니다 장애인 식당 하면 안 되는게 맞는데 내가 조금 화가 나고 어이가 없었던 것은 저희 동의 아파트 저희 동이 좀 작은 동 이에요 가지고 웬만하면 거기에 누가 누가 사는지도 뭐 대충 알고는 있는데 대부분 다 직장인들이고 젊은 층들이 많은데 아 그 장애인 주차장이다 한 군데가 있습니다 그래서 거기는 평소에 제가 이 5년전에 거기 이사를 갔는데 지금까지 거의 가 비어 있었던 적이 없어요 다 악의 축은 하면 다 피는 공간이게 하지만 아내는 주차 공간이 좀 부족해서 꽉 찹니다 그래서 이 좀 당연히 조 동향 나머지 4개 거길 됐고 법 앞에 경비실이 있기 때문에 너 저희들이 뭐 이 산나리 라던가 뭐 재활용 분리수거 날 뭐 이런 날에는 에 경비원들이 안내를 해주기 때문에 경비실에서 했 공략 크면 뭐 그냥 그런 위험 썼던 공간이죠 또 아파트니까 공동 주택이긴 하지만 어떻게 보면 개인의 주거 공간이기도 한 그것을 갖다가 뭐 그렇게 다 동의를 하는 부분이 있다면 그때 가는게 맞다 맞으니까 되는 께 저도 당연하게 거기에다 주차를 공간이 비어 있으면 주차를 하고 이랬던 부분인데 저희 아파트 제 동 앞에 어 장애인 주차 공간에 차를 댔다 난 이유로 과태료 맞았습니다 그러니까 5년 동안 살았는데 처음 맞은 거죠 문제는 정부 들어와서 저는 근데 그게 화가 납니다 바가 아 화가 나가지고 외관 한데 주차공간에 차를 댔다는 건 분명히 잘못된 거지만 이것은 지극히 사적인 어떤 그 이렇게 공동체 누구도 관여 해서는 안 되는 공동체고 공동체 안에 동의가 이루어졌다면 은 그걸 갖다가 정부가 정부 기관이 관여를 할 문제가 아니라고 보는 앞에서 뭐 회사 주차 자기 뜬 어떤 뭐 어떤 다른 건물에 주차 자기는 거기서 장애인 주차는 저는 하지를 않습니다 단지 저희 아파트는 원래 그려 왔으니까 저희 동에서는 그래서 했던건데 10만원 많이 꼭지가 확 돌더라구요\n\n[이하 내용이 매우 길어 전체를 정제하여 출력하겠습니다만, 전체 분량이 상당하므로 주요 수정사항을 중심으로 계속 진행하겠습니다]",
  "movie_id": "그랜 토리노",
  "reviewer": "작스튜브ZAKSTUBE",
  "chunk_index": 1
}