{
  "chunk_hash": "c2aa49ae6ab49d",
  "chunk_id": "정신과의사_뇌부자들_c2aa49ae6ab49d_4a86d025",
  "user_query": "약한 채로 살아남고 마에스트로 자리에 올라가기까지 엄청난 경멸과 무시를 당하지 않았을까 음 저는 어떻게 보면은 마음 한켠에 성진의 마음에도 이런 어떤 부 굉장 내가 가질 수 없는 이런 거대한 부에 대한 선망이 있기 때문에 이거를 좀 부정하고 싶어서 오히려 우리가 반동 형성이라고 하죠네 조금 더 이렇게 센 표현들로 어 이런 마음들을 표현하지 않았나라는 생각도 해 봤어요 음 그럴 수도 있겠네요 음 그러니까 뭔가 이제 이런 부를 이제 원한다면 굉장히 좀 그거는 속물적인 거고 내가 그동안 이제 추구해 온 약간은 고고한 가치들 아 이거 배치가 된다네 내가 이런 사람이라는 걸 받아들일 수가 없는 거죠 가면 증후군이 아닐까 그런 생각을 좀 해봤습니다 증후군이라는 거는 내가 현재 가지고 있는 어떤 지위 예 이런 자리들이 어 거품이다 사실 나는 요거밖에 안 되는 사람인데 이만큼 누리고 있다 그래서 언제고 나의 실체가 드러나고 어 내가 나락으로 떨어질 수 있다 약간 이런 불안을 가지고 있는 증후군을 이제 임포스터 신드롬 가면 증후군이라고 하거든요 내가 실제로는 자리에 맞지 않는 형편없는 능력을 가진 사람이다 이거는 정말 많은 분들이 느끼는 거예요 대기업 들어가신 분들이나 아니면 이제 뭐 전문직 혹은 뭐 이제 좋은 대학에 들어간 사람들도 다 어 나 실수로 뽑았나 이 사람들 나 실체를 알면 이럴 리가 없는데 음 근데 이제 성진은 그러니까 본인이 가지고 있는 분명 아니 오케스트라의 이제 그 마에스트로 자리나 사실 나의 정말 나의 능력이 아니라 사실 이런 백그라운드네 수연의 이런 후광 때문에 내가 이걸 누리고 있다라는 그런 마음 때문에 음 사실 그 안에서 되게 좀 부족함네 열등감 어떤 부적절감 등으로 좀 힘들어하지 않나 예 이런 생각을 좀 해봤습니다 음 근데 본격적인 마찰이 또 나오는 게 이제 오케스트라 연습을 하는데 딱 쉬는 시간에 마에스트로 자기는 앉아 있는데 이제 객석에서 지켜보던 단장인 어머니와 음 그리고 자신의 여자친구 이 첼리스트가 둘이서 음 토론을 하는 걸 보게 돼요네 공연을 어떻게 좀 만들어 갈지에 대해서 이야기를 하는 거죠 일반적으로는 사실은 오케스트라를 끌고 가는 지휘자와 이야기를 해야 될 부분인데 말하자면 지휘자를 패싱을 하고 이렇게 모녀가 둘이서 이야기를 하고 있는 모습을 보고 그 모든 단원들이 다 보는 가운데 음 예 거기서 정말 성진이 크게 화를 내거든요 지휘자는 그냥 허수아비라 거 사람들이 다 알게끔 해야 되는 거니 아니 그거는 꼭 거기서 그렇게 다 보는 자리에서 해야만 했어 날 이렇게 창피하게 만들어야 되냐 내가 허수아비 주의자인 거 뭐 알리려 그러냐 허수아비라는 단어를 실제로 썼어요 맞아요 예 왜 이렇게 화가 났을까 우리가 인생에서 가장 중요한 결정 중에 하나가 뭐죠 가장 중요한 결정 결혼 결혼이 누구랑 결혼하고 어떤 가정을 이룰 거냐라는 건데 거기서 진짜로 날 별로 좋아하지 않는 것 같은 사람을 어쨌든 받아들였고 그리고 부자에 대한 어떤 혐오감과 불편감도 있었을 텐데도 받아들였어요 그거는 그만큼 절실하게 필요했다는 거예요 그런",
  "movie_id": "히든페이스",
  "reviewer": "정신과의사_뇌부자들",
  "chunk_index": 3
}