{
  "chunk_hash": "f9dd9770b4e870",
  "chunk_id": "튜나_f9dd9770b4e870_fadcd645",
  "user_query": "코미디를 듣기에 바빴던 무룩이 이안을 만나자마자 대서 한두 마디에 우울해지는 이런 상황은 입체적인게 아니라 그냥 좋을 중이죠 최소한 설계자가 자신 안에 있다는 점 때문에 진지하게 고민하는 장면이 중간중간 삽입이 되었어야 이해할 수 있는 감정 선입니다 그런 거 없이 그냥 질러 버리니 주인공임에도 공감하고 이입하기 다이 감정이 어디서 왔는지 당황스럽 죠 문제의 출발도 급한데 해결도 급합니다 이렇게 급작스럽게 생긴 갈등은 바로 다음 사로 해결해 버려요이는네 안에 뭐가 있든 넌 너야 그냥 살아라는 지극히 카이스 결론을 내버립니다 물론 날씨의 [음악] 아이는이 결론에 달하기 위해서 시간 40분을 쓰지만 외계인은 1분 40초를 쓴다는 사소한 차이 정도가 있겠네요 과연 너는 도움이 안 되잖아 그지만 이게 내 감정이야 부부터 보인 비범함이 어디 가는 건 아닌가 봅니다 결과적으로이 무릎과 설계자의 공생관계는 무릎의 캐릭터성과 외계인 부에 있어서 핵심적인 문제지만 너무나 가볍게 다뤄지고 소모되고 맙니다 영화가 가야 할 길이 머니 다소의 생략은 어쩔 수 없지 않냐고요 그렇다기엔 이후에 등장하는 파트들이 통째로 드러내도 상관이 없는 민개 우왕 저왕 파트입니다 먼저 민개 민게이 그 일부 마지막에 총을 들고 가드를 쫓는 모습이 등장하며 그 정체에 대한 의문점을 남겼죠 전 민게이 일부에서 이안이 제대로 수행하지 못한 역할 화자의 역할을 해 줄 거라 생각했습니다 가드가 사실은 이안에게 따뜻한 감정을 가지고 있었다는 증거나 앰뷸런스는 어떻게 아무런 제지 없이 현장을 빠져 나왔는가 같은 이야기에 숭숭 뚫린 구멍을 메워주는 윤활유로 기능하는 한편 산기한 이야기를 어 모아서 하나의 줄기로 묶어내 주는 역할이요 보통 비상식적인 상황에 놓인 상식적인 인물이 맞는 롤이 을의 이렇게 마련이잖아요이 예상은 반만 맞고 반은 틀렸습니다 민계 이은 일부의 이야기를 되짚어 가며 어느 정도의 정리를 하긴 합니다 하지만 일부의 사건에 대한 또 다른 관점으로 일부의 캐릭터들의 서사를 강화하기보다 새로운 빌런을 추가해서 기존의 이야기에 편성시 방향성을 탑니다 당연히 민개 이과 새로운 빌런에 좀 더 초점이 맞춰지고 말죠 여기에 민개 이의 정체에 대한 새로운 떡밥까지 던지고 요가 장면 대응 팀과의 갈 등 그리고 제발 좀 자폭을 했으면 이제 좀 기능이 정지됐던 좋겠는 외계 로봇의 스피드 왜건 등 이야기에서 드러내도 아무런 문제가 없는 장면까지 이야기를 수습하기 다 더 벌려놓는 시간들이 진행되죠이 민갱 파트만에도 상당한 분량에 비해 위한 장면이 적은데 우왕 자왕의 이야기는 완벽하게 필요 없는 장면입니다 넌 너대로 그냥 살아를 시전하고 각자 갈길 가자는 이안과의 아름다운 이별도 잠시 무르군 마침 우연 희도 썬더의 행방을 알고 있어 있었기 때문에 다시 이안을 찾아가 썬더의 위치를 알려주기에 이릅니다 썬더와 감격해 제외를 하지만 썬더는 기능이 정지된 상태 어쩔 수 없이 썬더를 등에 걸쳐주고 다시 여정에 나서는 이안이 과정에서 우왕과 자왕 똑같이 생긴 나무꾼들이 지나가다 우왕과 자왕의 보고 혼기 백산 하며",
  "movie_id": "외계+인",
  "reviewer": "튜나",
  "chunk_index": 5,
  "entities": [
    {
      "record_type": "entity",
      "entity_name": "무룩",
      "entity_type": "MOVIE_CHARACTER",
      "entity_description": "무룩은 설계자와 공생관계를 가진 주인공 캐릭터로, 감정선이 급작스럽게 변화한다는 평가를 받는다"
    },
    {
      "record_type": "entity",
      "entity_name": "이안",
      "entity_type": "MOVIE_CHARACTER",
      "entity_description": "이안은 무룩과 관계를 맺는 인물로, 썬더의 행방을 알게 되며 여정을 떠나는 캐릭터이다"
    },
    {
      "record_type": "entity",
      "entity_name": "설계자",
      "entity_type": "MOVIE_CHARACTER",
      "entity_description": "설계자는 무룩 안에 존재하며 무룩과 공생관계를 가진 존재이다"
    },
    {
      "record_type": "entity",
      "entity_name": "민개",
      "entity_type": "MOVIE_CHARACTER",
      "entity_description": "민개는 일부의 이야기를 되짚어가며 정리하는 역할을 하는 캐릭터이다"
    },
    {
      "record_type": "entity",
      "entity_name": "가드",
      "entity_type": "MOVIE_CHARACTER",
      "entity_description": "가드는 이안에게 따뜻한 감정을 가지고 있었을 수 있는 인물로, 민개에게 쫓기는 장면이 등장한다"
    },
    {
      "record_type": "entity",
      "entity_name": "썬더",
      "entity_type": "MOVIE_CHARACTER",
      "entity_description": "썬더는 이안이 찾아 헤매는 대상으로, 기능이 정지된 상태로 발견된다"
    },
    {
      "record_type": "entity",
      "entity_name": "우왕",
      "entity_type": "MOVIE_CHARACTER",
      "entity_description": "우왕은 자왕과 똑같이 생긴 나무꾼 캐릭터이다"
    },
    {
      "record_type": "entity",
      "entity_name": "자왕",
      "entity_type": "MOVIE_CHARACTER",
      "entity_description": "자왕은 우왕과 똑같이 생긴 나무꾼 캐릭터이다"
    },
    {
      "record_type": "entity",
      "entity_name": "외계+인",
      "entity_type": "MOVIE",
      "entity_description": "외계+인은 무룩과 설계자의 공생관계, 이안의 여정 등을 다룬 한국 영화이다"
    },
    {
      "record_type": "entity",
      "entity_name": "날씨의 아이",
      "entity_type": "MOVIE",
      "entity_description": "날씨의 아이는 결론에 도달하기 위해 시간을 충분히 사용한 작품으로 외계+인과 비교되는 영화이다"
    }
  ],
  "relationships": [
    {
      "record_type": "relationship",
      "source_entity": "무룩",
      "source_type": "MOVIE_CHARACTER",
      "target_entity": "외계+인",
      "target_type": "MOVIE",
      "relationship_description": "무룩은 외계+인의 주인공이다",
      "relationship_strength": 10
    },
    {
      "record_type": "relationship",
      "source_entity": "이안",
      "source_type": "MOVIE_CHARACTER",
      "target_entity": "외계+인",
      "target_type": "MOVIE",
      "relationship_description": "이안은 외계+인에 등장하는 주요 캐릭터이다",
      "relationship_strength": 9
    },
    {
      "record_type": "relationship",
      "source_entity": "설계자",
      "source_type": "MOVIE_CHARACTER",
      "target_entity": "무룩",
      "target_type": "MOVIE_CHARACTER",
      "relationship_description": "설계자는 무룩 안에 존재하며 공생관계를 가진다",
      "relationship_strength": 10
    },
    {
      "record_type": "relationship",
      "source_entity": "민개",
      "source_type": "MOVIE_CHARACTER",
      "target_entity": "외계+인",
      "target_type": "MOVIE",
      "relationship_description": "민개는 외계+인에 등장하는 캐릭터이다",
      "relationship_strength": 8
    },
    {
      "record_type": "relationship",
      "source_entity": "민개",
      "source_type": "MOVIE_CHARACTER",
      "target_entity": "가드",
      "target_type": "MOVIE_CHARACTER",
      "relationship_description": "민개는 총을 들고 가드를 쫓는다",
      "relationship_strength": 7
    },
    {
      "record_type": "relationship",
      "source_entity": "이안",
      "source_type": "MOVIE_CHARACTER",
      "target_entity": "썬더",
      "target_type": "MOVIE_CHARACTER",
      "relationship_description": "이안은 썬더를 찾아 여정을 떠나며 썬더를 등에 걸쳐주고 다닌다",
      "relationship_strength": 9
    },
    {
      "record_type": "relationship",
      "source_entity": "무룩",
      "source_type": "MOVIE_CHARACTER",
      "target_entity": "이안",
      "target_type": "MOVIE_CHARACTER",
      "relationship_description": "무룩은 이안을 만나 감정 변화를 겪으며 썬더의 위치를 알려준다",
      "relationship_strength": 8
    },
    {
      "record_type": "relationship",
      "source_entity": "우왕",
      "source_type": "MOVIE_CHARACTER",
      "target_entity": "자왕",
      "target_type": "MOVIE_CHARACTER",
      "relationship_description": "우왕과 자왕은 똑같이 생긴 나무꾼들이다",
      "relationship_strength": 9
    },
    {
      "record_type": "relationship",
      "source_entity": "외계+인",
      "source_type": "MOVIE",
      "target_entity": "날씨의 아이",
      "target_type": "MOVIE",
      "relationship_description": "외계+인은 날씨의 아이와 결론 도달 시간 측면에서 비교된다",
      "relationship_strength": 5
    }
  ],
  "entity_resolution": {
    "무룩": {
      "description": "무룩 -> 무륵",
      "resolved_name": "무륵",
      "entity_type": "MOVIE_CHARACTER",
      "matched": true,
      "match_type": "synonym_exact"
    },
    "이안": {
      "description": "이안 -> 이안",
      "resolved_name": "이안",
      "entity_type": "MOVIE_CHARACTER",
      "matched": true,
      "match_type": "name_exact"
    },
    "설계자": {
      "description": "설계자 -> 설계자",
      "resolved_name": "설계자",
      "entity_type": "MOVIE_CHARACTER",
      "matched": false,
      "match_type": "not_found"
    },
    "민개": {
      "description": "민개 -> 민개",
      "resolved_name": "민개",
      "entity_type": "MOVIE_CHARACTER",
      "matched": false,
      "match_type": "not_found"
    },
    "가드": {
      "description": "가드 -> 가드",
      "resolved_name": "가드",
      "entity_type": "MOVIE_CHARACTER",
      "matched": true,
      "match_type": "name_exact"
    },
    "썬더": {
      "description": "썬더 -> 썬더",
      "resolved_name": "썬더",
      "entity_type": "MOVIE_CHARACTER",
      "matched": true,
      "match_type": "name_exact"
    },
    "우왕": {
      "description": "우왕 -> 우왕",
      "resolved_name": "우왕",
      "entity_type": "MOVIE_CHARACTER",
      "matched": true,
      "match_type": "name_exact"
    },
    "자왕": {
      "description": "자왕 -> 좌왕",
      "resolved_name": "좌왕",
      "entity_type": "MOVIE_CHARACTER",
      "matched": true,
      "match_type": "synonym_exact"
    },
    "외계+인": {
      "description": "외계+인 -> 외계+인",
      "resolved_name": "외계+인",
      "entity_type": "MOVIE",
      "matched": true,
      "match_type": "name_exact"
    },
    "날씨의 아이": {
      "description": "날씨의 아이 -> 날씨의 아이",
      "resolved_name": "날씨의 아이",
      "entity_type": "MOVIE",
      "matched": false,
      "match_type": "not_found"
    }
  }
}